README.rst
setup.cfg
setup.py
idxhound/__init__.py
idxhound.egg-info/PKG-INFO
idxhound.egg-info/SOURCES.txt
idxhound.egg-info/dependency_links.txt
idxhound.egg-info/requires.txt
idxhound.egg-info/top_level.txt