Metadata-Version: 2.1
Name: idxhound
Version: 0.3.0
Summary: UNKNOWN
Home-page: https://github.com/tillahoffmann/idxhound
Author: Till Hoffmann
License: UNKNOWN
Platform: UNKNOWN
